<?xml version="1.0" encoding="UTF-8"?><OASISReport xmlns="http://www.caiso.com/soa/OASISReport_v1.xsd">
<MessageHeader>
<TimeDate>2019-08-04T07:57:10-00:00</TimeDate>
<Source>OASIS</Source>
<Version>v20131201</Version>
</MessageHeader>
<MessagePayload>
<RTO>
<name>CAISO</name>
<REPORT_ITEM>
<REPORT_HEADER>
<SYSTEM>OASIS</SYSTEM>
<TZ>PPT</TZ>
<REPORT>ENE_LOSS</REPORT>
<MKT_TYPE>DAM</MKT_TYPE>
<UOM>MW</UOM>
<INTERVAL>ENDING</INTERVAL>
<SEC_PER_INTERVAL>3600</SEC_PER_INTERVAL>
</REPORT_HEADER>
<REPORT_DATA>
<DATA_ITEM>TOT_LOSS_MW</DATA_ITEM>
<OPR_DATE>2018-04-28</OPR_DATE>
<INTERVAL_NUM>2</INTERVAL_NUM>
<INTERVAL_START_GMT>2018-04-28T08:00:00-00:00</INTERVAL_START_GMT>
<INTERVAL_END_GMT>2018-04-28T09:00:00-00:00</INTERVAL_END_GMT>
<VALUE>165</VALUE>
</REPORT_DATA>
<REPORT_DATA>
<DATA_ITEM>TOT_LOSS_MW</DATA_ITEM>
<OPR_DATE>2018-04-28</OPR_DATE>
<INTERVAL_NUM>13</INTERVAL_NUM>
<INTERVAL_START_GMT>2018-04-28T19:00:00-00:00</INTERVAL_START_GMT>
<INTERVAL_END_GMT>2018-04-28T20:00:00-00:00</INTERVAL_END_GMT>
<VALUE>573.47</VALUE>
</REPORT_DATA>
<REPORT_DATA>
<DATA_ITEM>TOT_LOSS_MW</DATA_ITEM>
<OPR_DATE>2018-04-28</OPR_DATE>
<INTERVAL_NUM>11</INTERVAL_NUM>
<INTERVAL_START_GMT>2018-04-28T17:00:00-00:00</INTERVAL_START_GMT>
<INTERVAL_END_GMT>2018-04-28T18:00:00-00:00</INTERVAL_END_GMT>
<VALUE>995.67</VALUE>
</REPORT_DATA>
<REPORT_DATA>
<DATA_ITEM>TOT_LOSS_MW</DATA_ITEM>
<OPR_DATE>2018-04-28</OPR_DATE>
<INTERVAL_NUM>9</INTERVAL_NUM>
<INTERVAL_START_GMT>2018-04-28T15:00:00-00:00</INTERVAL_START_GMT>
<INTERVAL_END_GMT>2018-04-28T16:00:00-00:00</INTERVAL_END_GMT>
<VALUE>1157.89</VALUE>
</REPORT_DATA>
<REPORT_DATA>
<DATA_ITEM>TOT_LOSS_MW</DATA_ITEM>
<OPR_DATE>2018-04-28</OPR_DATE>
<INTERVAL_NUM>5</INTERVAL_NUM>
<INTERVAL_START_GMT>2018-04-28T11:00:00-00:00</INTERVAL_START_GMT>
<INTERVAL_END_GMT>2018-04-28T12:00:00-00:00</INTERVAL_END_GMT>
<VALUE>5.39</VALUE>
</REPORT_DATA>
<REPORT_DATA>
<DATA_ITEM>TOT_LOSS_MW</DATA_ITEM>
<OPR_DATE>2018-04-28</OPR_DATE>
<INTERVAL_NUM>17</INTERVAL_NUM>
<INTERVAL_START_GMT>2018-04-28T23:00:00-00:00</INTERVAL_START_GMT>
<INTERVAL_END_GMT>2018-04-29T00:00:00-00:00</INTERVAL_END_GMT>
<VALUE>821.95</VALUE>
</REPORT_DATA>
<REPORT_DATA>
<DATA_ITEM>TOT_LOSS_MW</DATA_ITEM>
<OPR_DATE>2018-04-28</OPR_DATE>
<INTERVAL_NUM>15</INTERVAL_NUM>
<INTERVAL_START_GMT>2018-04-28T21:00:00-00:00</INTERVAL_START_GMT>
<INTERVAL_END_GMT>2018-04-28T22:00:00-00:00</INTERVAL_END_GMT>
<VALUE>700.45</VALUE>
</REPORT_DATA>
<REPORT_DATA>
<DATA_ITEM>TOT_LOSS_MW</DATA_ITEM>
<OPR_DATE>2018-04-28</OPR_DATE>
<INTERVAL_NUM>4</INTERVAL_NUM>
<INTERVAL_START_GMT>2018-04-28T10:00:00-00:00</INTERVAL_START_GMT>
<INTERVAL_END_GMT>2018-04-28T11:00:00-00:00</INTERVAL_END_GMT>
<VALUE>22.71</VALUE>
</REPORT_DATA>
<REPORT_DATA>
<DATA_ITEM>TOT_LOSS_MW</DATA_ITEM>
<OPR_DATE>2018-04-28</OPR_DATE>
<INTERVAL_NUM>1</INTERVAL_NUM>
<INTERVAL_START_GMT>2018-04-28T07:00:00-00:00</INTERVAL_START_GMT>
<INTERVAL_END_GMT>2018-04-28T08:00:00-00:00</INTERVAL_END_GMT>
<VALUE>80.6</VALUE>
</REPORT_DATA>
<REPORT_DATA>
<DATA_ITEM>TOT_LOSS_MW</DATA_ITEM>
<OPR_DATE>2018-04-28</OPR_DATE>
<INTERVAL_NUM>19</INTERVAL_NUM>
<INTERVAL_START_GMT>2018-04-29T01:00:00-00:00</INTERVAL_START_GMT>
<INTERVAL_END_GMT>2018-04-29T02:00:00-00:00</INTERVAL_END_GMT>
<VALUE>1652.25</VALUE>
</REPORT_DATA>
<REPORT_DATA>
<DATA_ITEM>TOT_LOSS_MW</DATA_ITEM>
<OPR_DATE>2018-04-28</OPR_DATE>
<INTERVAL_NUM>10</INTERVAL_NUM>
<INTERVAL_START_GMT>2018-04-28T16:00:00-00:00</INTERVAL_START_GMT>
<INTERVAL_END_GMT>2018-04-28T17:00:00-00:00</INTERVAL_END_GMT>
<VALUE>1042.74</VALUE>
</REPORT_DATA>
<REPORT_DATA>
<DATA_ITEM>TOT_LOSS_MW</DATA_ITEM>
<OPR_DATE>2018-04-28</OPR_DATE>
<INTERVAL_NUM>6</INTERVAL_NUM>
<INTERVAL_START_GMT>2018-04-28T12:00:00-00:00</INTERVAL_START_GMT>
<INTERVAL_END_GMT>2018-04-28T13:00:00-00:00</INTERVAL_END_GMT>
<VALUE>217.51</VALUE>
</REPORT_DATA>
<REPORT_DATA>
<DATA_ITEM>TOT_LOSS_MW</DATA_ITEM>
<OPR_DATE>2018-04-28</OPR_DATE>
<INTERVAL_NUM>23</INTERVAL_NUM>
<INTERVAL_START_GMT>2018-04-29T05:00:00-00:00</INTERVAL_START_GMT>
<INTERVAL_END_GMT>2018-04-29T06:00:00-00:00</INTERVAL_END_GMT>
<VALUE>429.12</VALUE>
</REPORT_DATA>
<REPORT_DATA>
<DATA_ITEM>TOT_LOSS_MW</DATA_ITEM>
<OPR_DATE>2018-04-28</OPR_DATE>
<INTERVAL_NUM>14</INTERVAL_NUM>
<INTERVAL_START_GMT>2018-04-28T20:00:00-00:00</INTERVAL_START_GMT>
<INTERVAL_END_GMT>2018-04-28T21:00:00-00:00</INTERVAL_END_GMT>
<VALUE>583.47</VALUE>
</REPORT_DATA>
<REPORT_DATA>
<DATA_ITEM>TOT_LOSS_MW</DATA_ITEM>
<OPR_DATE>2018-04-28</OPR_DATE>
<INTERVAL_NUM>3</INTERVAL_NUM>
<INTERVAL_START_GMT>2018-04-28T09:00:00-00:00</INTERVAL_START_GMT>
<INTERVAL_END_GMT>2018-04-28T10:00:00-00:00</INTERVAL_END_GMT>
<VALUE>-41.94</VALUE>
</REPORT_DATA>
<REPORT_DATA>
<DATA_ITEM>TOT_LOSS_MW</DATA_ITEM>
<OPR_DATE>2018-04-28</OPR_DATE>
<INTERVAL_NUM>21</INTERVAL_NUM>
<INTERVAL_START_GMT>2018-04-29T03:00:00-00:00</INTERVAL_START_GMT>
<INTERVAL_END_GMT>2018-04-29T04:00:00-00:00</INTERVAL_END_GMT>
<VALUE>1241.41</VALUE>
</REPORT_DATA>
<REPORT_DATA>
<DATA_ITEM>TOT_LOSS_MW</DATA_ITEM>
<OPR_DATE>2018-04-28</OPR_DATE>
<INTERVAL_NUM>20</INTERVAL_NUM>
<INTERVAL_START_GMT>2018-04-29T02:00:00-00:00</INTERVAL_START_GMT>
<INTERVAL_END_GMT>2018-04-29T03:00:00-00:00</INTERVAL_END_GMT>
<VALUE>1518.27</VALUE>
</REPORT_DATA>
<REPORT_DATA>
<DATA_ITEM>TOT_LOSS_MW</DATA_ITEM>
<OPR_DATE>2018-04-28</OPR_DATE>
<INTERVAL_NUM>18</INTERVAL_NUM>
<INTERVAL_START_GMT>2018-04-29T00:00:00-00:00</INTERVAL_START_GMT>
<INTERVAL_END_GMT>2018-04-29T01:00:00-00:00</INTERVAL_END_GMT>
<VALUE>1636.23</VALUE>
</REPORT_DATA>
<REPORT_DATA>
<DATA_ITEM>TOT_LOSS_MW</DATA_ITEM>
<OPR_DATE>2018-04-28</OPR_DATE>
<INTERVAL_NUM>8</INTERVAL_NUM>
<INTERVAL_START_GMT>2018-04-28T14:00:00-00:00</INTERVAL_START_GMT>
<INTERVAL_END_GMT>2018-04-28T15:00:00-00:00</INTERVAL_END_GMT>
<VALUE>424.95</VALUE>
</REPORT_DATA>
<REPORT_DATA>
<DATA_ITEM>TOT_LOSS_MW</DATA_ITEM>
<OPR_DATE>2018-04-28</OPR_DATE>
<INTERVAL_NUM>22</INTERVAL_NUM>
<INTERVAL_START_GMT>2018-04-29T04:00:00-00:00</INTERVAL_START_GMT>
<INTERVAL_END_GMT>2018-04-29T05:00:00-00:00</INTERVAL_END_GMT>
<VALUE>1010.66</VALUE>
</REPORT_DATA>
<REPORT_DATA>
<DATA_ITEM>TOT_LOSS_MW</DATA_ITEM>
<OPR_DATE>2018-04-28</OPR_DATE>
<INTERVAL_NUM>12</INTERVAL_NUM>
<INTERVAL_START_GMT>2018-04-28T18:00:00-00:00</INTERVAL_START_GMT>
<INTERVAL_END_GMT>2018-04-28T19:00:00-00:00</INTERVAL_END_GMT>
<VALUE>713.14</VALUE>
</REPORT_DATA>
<REPORT_DATA>
<DATA_ITEM>TOT_LOSS_MW</DATA_ITEM>
<OPR_DATE>2018-04-28</OPR_DATE>
<INTERVAL_NUM>7</INTERVAL_NUM>
<INTERVAL_START_GMT>2018-04-28T13:00:00-00:00</INTERVAL_START_GMT>
<INTERVAL_END_GMT>2018-04-28T14:00:00-00:00</INTERVAL_END_GMT>
<VALUE>-162.59</VALUE>
</REPORT_DATA>
<REPORT_DATA>
<DATA_ITEM>TOT_LOSS_MW</DATA_ITEM>
<OPR_DATE>2018-04-28</OPR_DATE>
<INTERVAL_NUM>24</INTERVAL_NUM>
<INTERVAL_START_GMT>2018-04-29T06:00:00-00:00</INTERVAL_START_GMT>
<INTERVAL_END_GMT>2018-04-29T07:00:00-00:00</INTERVAL_END_GMT>
<VALUE>120.06</VALUE>
</REPORT_DATA>
<REPORT_DATA>
<DATA_ITEM>TOT_LOSS_MW</DATA_ITEM>
<OPR_DATE>2018-04-28</OPR_DATE>
<INTERVAL_NUM>16</INTERVAL_NUM>
<INTERVAL_START_GMT>2018-04-28T22:00:00-00:00</INTERVAL_START_GMT>
<INTERVAL_END_GMT>2018-04-28T23:00:00-00:00</INTERVAL_END_GMT>
<VALUE>675.81</VALUE>
</REPORT_DATA>
</REPORT_ITEM>
<REPORT_ITEM>
<REPORT_HEADER>
<SYSTEM>OASIS</SYSTEM>
<TZ>PPT</TZ>
<REPORT>ENE_LOSS</REPORT>
<MKT_TYPE>DAM</MKT_TYPE>
<UOM>US$</UOM>
<INTERVAL>ENDING</INTERVAL>
<SEC_PER_INTERVAL>3600</SEC_PER_INTERVAL>
</REPORT_HEADER>
<REPORT_DATA>
<DATA_ITEM>TOT_LOSS_PRC</DATA_ITEM>
<OPR_DATE>2018-04-28</OPR_DATE>
<INTERVAL_NUM>2</INTERVAL_NUM>
<INTERVAL_START_GMT>2018-04-28T08:00:00-00:00</INTERVAL_START_GMT>
<INTERVAL_END_GMT>2018-04-28T09:00:00-00:00</INTERVAL_END_GMT>
<VALUE>2788.11885</VALUE>
</REPORT_DATA>
<REPORT_DATA>
<DATA_ITEM>TOT_LOSS_PRC</DATA_ITEM>
<OPR_DATE>2018-04-28</OPR_DATE>
<INTERVAL_NUM>11</INTERVAL_NUM>
<INTERVAL_START_GMT>2018-04-28T17:00:00-00:00</INTERVAL_START_GMT>
<INTERVAL_END_GMT>2018-04-28T18:00:00-00:00</INTERVAL_END_GMT>
<VALUE>-4152.83005</VALUE>
</REPORT_DATA>
<REPORT_DATA>
<DATA_ITEM>TOT_LOSS_PRC</DATA_ITEM>
<OPR_DATE>2018-04-28</OPR_DATE>
<INTERVAL_NUM>5</INTERVAL_NUM>
<INTERVAL_START_GMT>2018-04-28T11:00:00-00:00</INTERVAL_START_GMT>
<INTERVAL_END_GMT>2018-04-28T12:00:00-00:00</INTERVAL_END_GMT>
<VALUE>88.35541</VALUE>
</REPORT_DATA>
<REPORT_DATA>
<DATA_ITEM>TOT_LOSS_PRC</DATA_ITEM>
<OPR_DATE>2018-04-28</OPR_DATE>
<INTERVAL_NUM>17</INTERVAL_NUM>
<INTERVAL_START_GMT>2018-04-28T23:00:00-00:00</INTERVAL_START_GMT>
<INTERVAL_END_GMT>2018-04-29T00:00:00-00:00</INTERVAL_END_GMT>
<VALUE>-875.44251</VALUE>
</REPORT_DATA>
<REPORT_DATA>
<DATA_ITEM>TOT_LOSS_PRC</DATA_ITEM>
<OPR_DATE>2018-04-28</OPR_DATE>
<INTERVAL_NUM>15</INTERVAL_NUM>
<INTERVAL_START_GMT>2018-04-28T21:00:00-00:00</INTERVAL_START_GMT>
<INTERVAL_END_GMT>2018-04-28T22:00:00-00:00</INTERVAL_END_GMT>
<VALUE>-5003.93075</VALUE>
</REPORT_DATA>
<REPORT_DATA>
<DATA_ITEM>TOT_LOSS_PRC</DATA_ITEM>
<OPR_DATE>2018-04-28</OPR_DATE>
<INTERVAL_NUM>4</INTERVAL_NUM>
<INTERVAL_START_GMT>2018-04-28T10:00:00-00:00</INTERVAL_START_GMT>
<INTERVAL_END_GMT>2018-04-28T11:00:00-00:00</INTERVAL_END_GMT>
<VALUE>312.73918</VALUE>
</REPORT_DATA>
<REPORT_DATA>
<DATA_ITEM>TOT_LOSS_PRC</DATA_ITEM>
<OPR_DATE>2018-04-28</OPR_DATE>
<INTERVAL_NUM>1</INTERVAL_NUM>
<INTERVAL_START_GMT>2018-04-28T07:00:00-00:00</INTERVAL_START_GMT>
<INTERVAL_END_GMT>2018-04-28T08:00:00-00:00</INTERVAL_END_GMT>
<VALUE>1530.88738</VALUE>
</REPORT_DATA>
<REPORT_DATA>
<DATA_ITEM>TOT_LOSS_PRC</DATA_ITEM>
<OPR_DATE>2018-04-28</OPR_DATE>
<INTERVAL_NUM>19</INTERVAL_NUM>
<INTERVAL_START_GMT>2018-04-29T01:00:00-00:00</INTERVAL_START_GMT>
<INTERVAL_END_GMT>2018-04-29T02:00:00-00:00</INTERVAL_END_GMT>
<VALUE>55102.35575</VALUE>
</REPORT_DATA>
<REPORT_DATA>
<DATA_ITEM>TOT_LOSS_PRC</DATA_ITEM>
<OPR_DATE>2018-04-28</OPR_DATE>
<INTERVAL_NUM>10</INTERVAL_NUM>
<INTERVAL_START_GMT>2018-04-28T16:00:00-00:00</INTERVAL_START_GMT>
<INTERVAL_END_GMT>2018-04-28T17:00:00-00:00</INTERVAL_END_GMT>
<VALUE>-1660.83456</VALUE>
</REPORT_DATA>
<REPORT_DATA>
<DATA_ITEM>TOT_LOSS_PRC</DATA_ITEM>
<OPR_DATE>2018-04-28</OPR_DATE>
<INTERVAL_NUM>6</INTERVAL_NUM>
<INTERVAL_START_GMT>2018-04-28T12:00:00-00:00</INTERVAL_START_GMT>
<INTERVAL_END_GMT>2018-04-28T13:00:00-00:00</INTERVAL_END_GMT>
<VALUE>5260.65336</VALUE>
</REPORT_DATA>
<REPORT_DATA>
<DATA_ITEM>TOT_LOSS_PRC</DATA_ITEM>
<OPR_DATE>2018-04-28</OPR_DATE>
<INTERVAL_NUM>23</INTERVAL_NUM>
<INTERVAL_START_GMT>2018-04-29T05:00:00-00:00</INTERVAL_START_GMT>
<INTERVAL_END_GMT>2018-04-29T06:00:00-00:00</INTERVAL_END_GMT>
<VALUE>11673.80623</VALUE>
</REPORT_DATA>
<REPORT_DATA>
<DATA_ITEM>TOT_LOSS_PRC</DATA_ITEM>
<OPR_DATE>2018-04-28</OPR_DATE>
<INTERVAL_NUM>14</INTERVAL_NUM>
<INTERVAL_START_GMT>2018-04-28T20:00:00-00:00</INTERVAL_START_GMT>
<INTERVAL_END_GMT>2018-04-28T21:00:00-00:00</INTERVAL_END_GMT>
<VALUE>-4308.37165</VALUE>
</REPORT_DATA>
<REPORT_DATA>
<DATA_ITEM>TOT_LOSS_PRC</DATA_ITEM>
<OPR_DATE>2018-04-28</OPR_DATE>
<INTERVAL_NUM>3</INTERVAL_NUM>
<INTERVAL_START_GMT>2018-04-28T09:00:00-00:00</INTERVAL_START_GMT>
<INTERVAL_END_GMT>2018-04-28T10:00:00-00:00</INTERVAL_END_GMT>
<VALUE>-640.94218</VALUE>
</REPORT_DATA>
<REPORT_DATA>
<DATA_ITEM>TOT_LOSS_PRC</DATA_ITEM>
<OPR_DATE>2018-04-28</OPR_DATE>
<INTERVAL_NUM>21</INTERVAL_NUM>
<INTERVAL_START_GMT>2018-04-29T03:00:00-00:00</INTERVAL_START_GMT>
<INTERVAL_END_GMT>2018-04-29T04:00:00-00:00</INTERVAL_END_GMT>
<VALUE>65685.908</VALUE>
</REPORT_DATA>
<REPORT_DATA>
<DATA_ITEM>TOT_LOSS_PRC</DATA_ITEM>
<OPR_DATE>2018-04-28</OPR_DATE>
<INTERVAL_NUM>20</INTERVAL_NUM>
<INTERVAL_START_GMT>2018-04-29T02:00:00-00:00</INTERVAL_START_GMT>
<INTERVAL_END_GMT>2018-04-29T03:00:00-00:00</INTERVAL_END_GMT>
<VALUE>66385.90027</VALUE>
</REPORT_DATA>
<REPORT_DATA>
<DATA_ITEM>TOT_LOSS_PRC</DATA_ITEM>
<OPR_DATE>2018-04-28</OPR_DATE>
<INTERVAL_NUM>18</INTERVAL_NUM>
<INTERVAL_START_GMT>2018-04-29T00:00:00-00:00</INTERVAL_START_GMT>
<INTERVAL_END_GMT>2018-04-29T01:00:00-00:00</INTERVAL_END_GMT>
<VALUE>3824.50764</VALUE>
</REPORT_DATA>
<REPORT_DATA>
<DATA_ITEM>TOT_LOSS_PRC</DATA_ITEM>
<OPR_DATE>2018-04-28</OPR_DATE>
<INTERVAL_NUM>8</INTERVAL_NUM>
<INTERVAL_START_GMT>2018-04-28T14:00:00-00:00</INTERVAL_START_GMT>
<INTERVAL_END_GMT>2018-04-28T15:00:00-00:00</INTERVAL_END_GMT>
<VALUE>4300.12854</VALUE>
</REPORT_DATA>
<REPORT_DATA>
<DATA_ITEM>TOT_LOSS_PRC</DATA_ITEM>
<OPR_DATE>2018-04-28</OPR_DATE>
<INTERVAL_NUM>22</INTERVAL_NUM>
<INTERVAL_START_GMT>2018-04-29T04:00:00-00:00</INTERVAL_START_GMT>
<INTERVAL_END_GMT>2018-04-29T05:00:00-00:00</INTERVAL_END_GMT>
<VALUE>44350.39862</VALUE>
</REPORT_DATA>
<REPORT_DATA>
<DATA_ITEM>TOT_LOSS_PRC</DATA_ITEM>
<OPR_DATE>2018-04-28</OPR_DATE>
<INTERVAL_NUM>12</INTERVAL_NUM>
<INTERVAL_START_GMT>2018-04-28T18:00:00-00:00</INTERVAL_START_GMT>
<INTERVAL_END_GMT>2018-04-28T19:00:00-00:00</INTERVAL_END_GMT>
<VALUE>-3820.46927</VALUE>
</REPORT_DATA>
<REPORT_DATA>
<DATA_ITEM>TOT_LOSS_PRC</DATA_ITEM>
<OPR_DATE>2018-04-28</OPR_DATE>
<INTERVAL_NUM>7</INTERVAL_NUM>
<INTERVAL_START_GMT>2018-04-28T13:00:00-00:00</INTERVAL_START_GMT>
<INTERVAL_END_GMT>2018-04-28T14:00:00-00:00</INTERVAL_END_GMT>
<VALUE>-5070.36427</VALUE>
</REPORT_DATA>
<REPORT_DATA>
<DATA_ITEM>TOT_LOSS_PRC</DATA_ITEM>
<OPR_DATE>2018-04-28</OPR_DATE>
<INTERVAL_NUM>24</INTERVAL_NUM>
<INTERVAL_START_GMT>2018-04-29T06:00:00-00:00</INTERVAL_START_GMT>
<INTERVAL_END_GMT>2018-04-29T07:00:00-00:00</INTERVAL_END_GMT>
<VALUE>2472.52284</VALUE>
</REPORT_DATA>
<REPORT_DATA>
<DATA_ITEM>TOT_LOSS_PRC</DATA_ITEM>
<OPR_DATE>2018-04-28</OPR_DATE>
<INTERVAL_NUM>16</INTERVAL_NUM>
<INTERVAL_START_GMT>2018-04-28T22:00:00-00:00</INTERVAL_START_GMT>
<INTERVAL_END_GMT>2018-04-28T23:00:00-00:00</INTERVAL_END_GMT>
<VALUE>-4183.28417</VALUE>
</REPORT_DATA>
<REPORT_DATA>
<DATA_ITEM>TOT_LOSS_PRC</DATA_ITEM>
<OPR_DATE>2018-04-28</OPR_DATE>
<INTERVAL_NUM>13</INTERVAL_NUM>
<INTERVAL_START_GMT>2018-04-28T19:00:00-00:00</INTERVAL_START_GMT>
<INTERVAL_END_GMT>2018-04-28T20:00:00-00:00</INTERVAL_END_GMT>
<VALUE>-4101.01587</VALUE>
</REPORT_DATA>
<REPORT_DATA>
<DATA_ITEM>TOT_LOSS_PRC</DATA_ITEM>
<OPR_DATE>2018-04-28</OPR_DATE>
<INTERVAL_NUM>9</INTERVAL_NUM>
<INTERVAL_START_GMT>2018-04-28T15:00:00-00:00</INTERVAL_START_GMT>
<INTERVAL_END_GMT>2018-04-28T16:00:00-00:00</INTERVAL_END_GMT>
<VALUE>1188.36566</VALUE>
</REPORT_DATA>
</REPORT_ITEM>
<DISCLAIMER_ITEM>
<DISCLAIMER>The contents of these pages are subject to change without notice.  Decisions based on information contained within the California ISO's web site are the visitor's sole responsibility.</DISCLAIMER>
</DISCLAIMER_ITEM>
</RTO>
</MessagePayload>
</OASISReport>
